nemo_curator/__init__.py
nemo_curator/_compat.py
nemo_curator/log.py
nemo_curator/sample_dataframe.py
nemo_curator/datasets/__init__.py
nemo_curator/datasets/doc_dataset.py
nemo_curator/download/__init__.py
nemo_curator/download/arxiv.py
nemo_curator/download/commoncrawl.py
nemo_curator/download/doc_builder.py
nemo_curator/download/wikipedia.py
nemo_curator/filters/__init__.py
nemo_curator/filters/classifier_filter.py
nemo_curator/filters/code.py
nemo_curator/filters/doc_filter.py
nemo_curator/filters/heuristic_filter.py
nemo_curator/modifiers/__init__.py
nemo_curator/modifiers/c4.py
nemo_curator/modifiers/doc_modifier.py
nemo_curator/modifiers/fasttext.py
nemo_curator/modifiers/pii_modifier.py
nemo_curator/modifiers/unicode_reformatter.py
nemo_curator/modules/__init__.py
nemo_curator/modules/add_id.py
nemo_curator/modules/config.py
nemo_curator/modules/dataset_ops.py
nemo_curator/modules/distributed_data_classifier.py
nemo_curator/modules/exact_dedup.py
nemo_curator/modules/filter.py
nemo_curator/modules/fuzzy_dedup.py
nemo_curator/modules/meta.py
nemo_curator/modules/modify.py
nemo_curator/modules/semantic_dedup.py
nemo_curator/modules/task.py
nemo_curator/nemo_run/__init__.py
nemo_curator/nemo_run/slurm.py
nemo_curator/pii/__init__.py
nemo_curator/pii/algorithm.py
nemo_curator/pii/constants.py
nemo_curator/pii/custom_batch_analyzer_engine.py
nemo_curator/pii/custom_nlp_engine.py
nemo_curator/pii/recognizers/__init__.py
nemo_curator/pii/recognizers/address_recognizer.py
nemo_curator/scripts/__init__.py
nemo_curator/scripts/add_id.py
nemo_curator/scripts/blend_datasets.py
nemo_curator/scripts/domain_classifier_inference.py
nemo_curator/scripts/download_and_extract.py
nemo_curator/scripts/filter_documents.py
nemo_curator/scripts/find_exact_duplicates.py
nemo_curator/scripts/find_matching_ngrams.py
nemo_curator/scripts/find_pii_and_deidentify.py
nemo_curator/scripts/get_common_crawl_urls.py
nemo_curator/scripts/get_wikipedia_urls.py
invisible_unicorn-0.4.0.dist-info/LICENSE
invisible_unicorn-0.4.0.dist-info/METADATA
invisible_unicorn-0.4.0.dist-info/WHEEL
invisible_unicorn-0.4.0.dist-info/entry_points.txt
invisible_unicorn-0.4.0.dist-info/top_level.txt
invisible_unicorn-0.4.0.dist-info/RECORD
