Metadata-Version: 2.1
Name: invisible_unicorn
Version: 0.4.0
Summary: Scalable Data Preprocessing Tool for Training Large Language Models
Home-page: https://github.com/NVIDIA/NeMo-Curator
Author: Joseph Jennings, Mostofa Patwary, Sandeep Subramanian, Shrimai Prabhumoye, Ayush Dattagupta, Vibhu Jawa, Jiwei Liu, Ryan Wolf
Author-email: jjennings@nvidia.com, mpatwary@nvidia.com, rywolf@nvidia.com, sprabhumoye@nvidia.com
Classifier: Development Status :: 3 - Alpha
Classifier: Programming Language :: Python :: 3
Classifier: Programming Language :: Python :: 3.10
Requires-Python: >=3.10, <3.11
License-File: LICENSE
Requires-Dist: dask[complete] >=2021.7.1
Requires-Dist: distributed >=2021.7.1
Requires-Dist: dask-mpi >=2021.11.0
Requires-Dist: charset-normalizer >=3.1.0
Requires-Dist: awscli >=1.22.55
Requires-Dist: fasttext ==0.9.2
Requires-Dist: pycld2
Requires-Dist: justext ==3.0.1
Requires-Dist: resiliparse
Requires-Dist: ftfy ==6.1.1
Requires-Dist: warcio ==1.7.4
Requires-Dist: zstandard ==0.18.0
Requires-Dist: in-place ==0.5.0
Requires-Dist: unidic-lite ==1.0.8
Requires-Dist: jieba ==0.42.1
Requires-Dist: comment-parser
Requires-Dist: beautifulsoup4
Requires-Dist: mwparserfromhell ==0.6.5
Requires-Dist: spacy <3.8,>=3.6.0
Requires-Dist: presidio-analyzer ==2.2.351
Requires-Dist: presidio-anonymizer ==2.2.351
Requires-Dist: usaddress ==0.5.10
Requires-Dist: nemo-toolkit[nlp] >=1.23.0
Requires-Dist: Cython
Requires-Dist: crossfit ==0.0.4
Requires-Dist: numpy <2
Requires-Dist: openai
Provides-Extra: cuda12x
Requires-Dist: cudf-cu12 ==24.6.* ; extra == 'cuda12x'
Requires-Dist: dask-cudf-cu12 ==24.6.* ; extra == 'cuda12x'
Requires-Dist: cuml-cu12 ==24.6.* ; extra == 'cuda12x'
Requires-Dist: cugraph-cu12 ==24.6.* ; extra == 'cuda12x'
Requires-Dist: dask-cuda ==24.6.* ; extra == 'cuda12x'
Requires-Dist: spacy[cuda12x] <3.8,>=3.6.0 ; extra == 'cuda12x'
